eddy_mc-0.3.6.data/scripts/eddy
eddymc/__init__.py
eddymc/eddy.py
eddymc/mcnp/__init__.py
eddymc/mcnp/cells.py
eddymc/mcnp/cerberus_logo.py
eddymc/mcnp/eddy_mcnp_case.py
eddymc/mcnp/mcnp_html_writer.py
eddymc/mcnp/particles.py
eddymc/mcnp/tallies.py
eddymc/scale/__init__.py
eddymc/scale/eddy_scale_case.py
eddymc/scale/mixtures.py
eddymc/scale/scale_html_writer.py
eddymc/scale/scale_tallies.py
eddymc/static/MCNP_template.html
eddymc/static/SCALE_template.html
eddymc/static/__init__.py
eddymc/static/style.css
eddy_mc-0.3.6.dist-info/LICENSE
eddy_mc-0.3.6.dist-info/METADATA
eddy_mc-0.3.6.dist-info/WHEEL
eddy_mc-0.3.6.dist-info/top_level.txt
eddy_mc-0.3.6.dist-info/RECORD
